[
    {
        "name": "Monitor",
        "product_id": "P8081",
        "price": 234.56,
        "description": "This movement positive. Painting deal offer provide. Large example news significant environmental.",
        "creation_date": "2024-10-09"
    },
    {
        "name": "Printer",
        "product_id": "P2807",
        "price": 235.31,
        "description": "Process star either yes gas room trial. Arm school entire benefit.",
        "creation_date": "2024-10-09"
    },
    {
        "name": "Router",
        "product_id": "P3033",
        "price": 166.27,
        "description": "Institution hour wait per second.",
        "creation_date": "2024-10-09"
    },
    {
        "name": "Laptop",
        "product_id": "P5984",
        "price": 856.36,
        "description": "Collection inside girl hope produce fill. Any between increase road.",
        "creation_date": "2024-10-09"
    },
    {
        "name": "Mouse",
        "product_id": "P6609",
        "price": 31.23,
        "description": "Clearly similar include middle assume. Necessary eye social line.",
        "creation_date": "2024-10-09"
    },
    {
        "name": "Smartwatch",
        "product_id": "P4337",
        "price": 109.32,
        "description": "Player myself allow.",
        "creation_date": "2024-10-10"
    },
    {
        "name": "Smartphone",
        "product_id": "P2152",
        "price": 764.78,
        "description": "Set behind someone should. Degree but subject everybody.\nIt or cover city every it pretty.",
        "creation_date": "2024-10-11"
    },
    {
        "name": "Headphones",
        "product_id": "P4150",
        "price": 181.82,
        "description": "Specific small increase season. Former place test method quality.",
        "creation_date": "2024-10-12"
    },
    {
        "name": "Camera",
        "product_id": "P5373",
        "price": 988.86,
        "description": "Maybe key agency only trial.",
        "creation_date": "2024-10-13"
    },
    {
        "name": "External Hard Drive",
        "product_id": "P9371",
        "price": 103.34,
        "description": "Appear people poor strategy.",
        "creation_date": "2024-10-14"
    },
    {
        "name": "Tablet",
        "product_id": "P3859",
        "price": 459.58,
        "description": "Increase it a hour think. Return anyone blue measure.",
        "creation_date": "2024-10-15"
    },
    {
        "name": "Keyboard",
        "product_id": "P5047",
        "price": 131.55,
        "description": "Piece someone person woman ability back member. Challenge source push. Growth TV character.",
        "creation_date": "2024-10-16"
    }
]